stupidArtnet/ArtnetUtils.py
stupidArtnet/StupidArtnet.py
stupidArtnet/StupidArtnetServer.py
stupidArtnet/__init__.py
stupidartnet-1.6.0.dist-info/LICENSE
stupidartnet-1.6.0.dist-info/METADATA
stupidartnet-1.6.0.dist-info/WHEEL
stupidartnet-1.6.0.dist-info/top_level.txt
stupidartnet-1.6.0.dist-info/RECORD
