Metadata-Version: 2.2
Name: stupidArtnet
Version: 1.6.0
Summary: (Very) Simple implementation of the Art-Net protocol
Home-page: https://github.com/cpvalente/stupidArtnet
Author: cpvalente
License: MIT
Project-URL: Bug Tracker, https://github.com/cpvalente/stupidArtnet/issues
Keywords: LIGHTING,DMX,LIGHTING CONTROL
Classifier: Programming Language :: Python :: 3
Classifier: License :: OSI Approved :: MIT License
Classifier: Operating System :: OS Independent
Requires-Python: >=3.6
License-File: LICENSE
Dynamic: author
Dynamic: classifier
Dynamic: description
Dynamic: description-content-type
Dynamic: home-page
Dynamic: keywords
Dynamic: license
Dynamic: project-url
Dynamic: requires-python
Dynamic: summary
